morph/__init__.py
morph/cli/README.md
morph/cli/__init__.py
morph/cli/flags.py
morph/cli/main.py
morph/cli/params.py
morph/cli/requires.py
morph/cli/types.py
morph/task/__init__.py
morph/task/base.py
morph/task/constant/__init__.py
morph/task/constant/project_config.py
morph/task/constant/pyproject_template.toml
morph/task/file.py
morph/task/init.py
morph/task/new.py
morph/task/print.py
morph/task/run.py
morph/task/sync.py
morph/task/utils/__init__.py
morph/task/utils/code_execution.py
morph/task/utils/decorator.py
morph/task/utils/logging.py
morph/task/utils/morph.py
morph/task/utils/sql.py
morph/task/utils/sqlite.py
morph/task/utils/status.py
morph/task/utils/timer.py
morph/task/utils/timezone.py
morphdb_utils/__init__.py
morphdb_utils/annotations.py
morphdb_utils/api.py
morphdb_utils/logging.py
morphdb_utils/py.typed
morphdb_utils/type.py
morphdb_utils/utils/__init__.py
morphdb_utils/utils/config.py
morphdb_utils/utils/env.py
morphdb_utils/utils/helper.py
morphdb_utils/utils/request.py
morphdb_utils/utils/response.py
morphdb_utils/utils/sql.py
morph_cli-0.2.39.dist-info/METADATA
morph_cli-0.2.39.dist-info/WHEEL
morph_cli-0.2.39.dist-info/entry_points.txt
morph_cli-0.2.39.dist-info/RECORD
